setup.py
funniest__test2016/__init__.py
funniest_test2016.egg-info/PKG-INFO
funniest_test2016.egg-info/SOURCES.txt
funniest_test2016.egg-info/dependency_links.txt
funniest_test2016.egg-info/not-zip-safe
funniest_test2016.egg-info/top_level.txt